<?xml version = '1.0' encoding = 'UTF-8'?>
<Process class="oracle.dbtools.crest.model.design.process.Process" name="Sprzedarz pojazdu z listy" directorySegmentName="seg_0" id="13432534-2FE9-B69A-485C-3ECBA7FC9A22">
<createdBy>Biolog</createdBy>
<createdTime>2021-04-06 15:01:22 UTC</createdTime>
<ownerDesignName>projektBazodanowyV3</ownerDesignName>
<primary>false</primary>
<batchMinimumTransactions>1000</batchMinimumTransactions>
<batchTimeUnit>Second</batchTimeUnit>
<footNote>Wlasciciel sprzedaje samochod w salonie stacjonarnym</footNote>
<frequencyTimeUnit>Day</frequencyTimeUnit>
<frequencyTimes>0</frequencyTimes>
<interactiveLongestResponseTime>5</interactiveLongestResponseTime>
<interactiveResponseTimeUnit>Second</interactiveResponseTimeUnit>
<mode>Unknown</mode>
<priority>Low</priority>
<peakPeriodsString>000000000000000000000000</peakPeriodsString>
</Process>